LICENSE
README.md
mcp_server/__init__.py
mcp_server/debug_mcp_wrapper.py
mcp_server/debug_uvx_wrapper.py
mcp_server/mcp_wrapper.py
mcp_server/prompt_mcp_server.py
tests/README.md
tests/results/README.md
tools/README.md
prompt_mcp_server-2.0.9.dist-info/METADATA
prompt_mcp_server-2.0.9.dist-info/WHEEL
prompt_mcp_server-2.0.9.dist-info/entry_points.txt
prompt_mcp_server-2.0.9.dist-info/licenses/LICENSE
prompt_mcp_server-2.0.9.dist-info/RECORD
