Metadata-Version: 2.4
Name: prompt-mcp-server
Version: 2.0.9
Summary: MCP server for Amazon Q Developer CLI that manages prompt files
Project-URL: Homepage, https://github.com/amazon-q-developer/prompt-mcp-server
Project-URL: Repository, https://github.com/amazon-q-developer/prompt-mcp-server
Project-URL: Issues, https://github.com/amazon-q-developer/prompt-mcp-server/issues
Project-URL: Documentation, https://github.com/amazon-q-developer/prompt-mcp-server#readme
Project-URL: Changelog, https://github.com/amazon-q-developer/prompt-mcp-server/releases
Author: Amazon Q Developer CLI Team
License: MIT
License-File: LICENSE
Keywords: ai,amazon-q,cli,mcp,model-context-protocol,prompts
Classifier: Development Status :: 5 - Production/Stable
Classifier: Environment :: Console
Classifier: Intended Audience :: Developers
Classifier: License :: OSI Approved :: MIT License
Classifier: Programming Language :: Python :: 3
Classifier: Programming Language :: Python :: 3.6
Classifier: Programming Language :: Python :: 3.7
Classifier: Programming Language :: Python :: 3.8
Classifier: Programming Language :: Python :: 3.9
Classifier: Programming Language :: Python :: 3.10
Classifier: Programming Language :: Python :: 3.11
Classifier: Programming Language :: Python :: 3.12
Classifier: Topic :: Communications
Classifier: Topic :: Software Development
Classifier: Topic :: Utilities
Requires-Python: >=3.6
Provides-Extra: dev
Requires-Dist: pytest-asyncio>=0.21.0; extra == 'dev'
Requires-Dist: pytest>=7.0; extra == 'dev'
Provides-Extra: test
Requires-Dist: pytest-asyncio>=0.21.0; extra == 'test'
Requires-Dist: pytest>=7.0; extra == 'test'
